jetzt/__init__.py
jetzt/check_for_updates.py
jetzt/check_if_installed.py
jetzt/cli.py
jetzt/create_reqs.py
jetzt/list_installed.py
jetzt/update_metadata.py
jetzt/bin/create_reqs.sh
jetzt/bin/install_pypi_pkg.sh
jetzt/bin/jetzt_scaffold.sh
jetzt/bin/list_outdated_pkgs.sh
jetzt/bin/list_pkgs.sh
jetzt/bin/reinstall_reqs.sh
jetzt/bin/remove_pkg.sh
jetzt/bin/update_pypi_pkg.sh
jetzt/seeds/python_jupyter/starting-point.ipynb
jetzt-0.6.6.dist-info/LICENSE
jetzt-0.6.6.dist-info/METADATA
jetzt-0.6.6.dist-info/WHEEL
jetzt-0.6.6.dist-info/entry_points.txt
jetzt-0.6.6.dist-info/top_level.txt
jetzt-0.6.6.dist-info/RECORD
