Metadata-Version: 2.1
Name: jetzt
Version: 0.6.6
Summary: Light-weight project manager for Python projects.
Home-page: https://github.com/janikarh/jetzt
Author: Jani Karhunen
Author-email: janikarh@gmail.com
License: MIT
Platform: UNKNOWN
Classifier: License :: OSI Approved :: MIT License
Classifier: Programming Language :: Python
Classifier: Programming Language :: Python :: 3
Classifier: Programming Language :: Python :: 3.6
Classifier: Programming Language :: Python :: 3.7
Classifier: Topic :: Utilities
Requires-Python: >=3.6.0
Requires-Dist: Click (<8.0,>=7.0)
Requires-Dist: bullet (<3.0.0,>=2.1.0)
Requires-Dist: colorama (<=0.4.3,>=0.3.9)
